executing/__init__.py
executing/executing.py
executing/version.py
executing-0.8.1.dist-info/LICENSE.txt
executing-0.8.1.dist-info/METADATA
executing-0.8.1.dist-info/WHEEL
executing-0.8.1.dist-info/top_level.txt
executing-0.8.1.dist-info/RECORD
